Metadata-Version: 2.1
Name: odoo12-addon-l10n-it-invoices-data-communication
Version: 12.0.1.3.2
Summary: Comunicazione dati fatture (c.d. "nuovo spesometro" o "esterometro")
Home-page: https://github.com/OCA/l10n-italy/
Author: Openforce di Camilli Alessandro, Odoo Community Association (OCA)
Author-email: support@odoo-community.org
License: AGPL-3
Platform: UNKNOWN
Classifier: Programming Language :: Python
Classifier: Framework :: Odoo
Classifier: License :: OSI Approved :: GNU Affero General Public License v3
Requires-Python: >=3.5
Requires-Dist: odoo12-addon-l10n-it-account
Requires-Dist: odoo12-addon-l10n-it-account-tax-kind
Requires-Dist: odoo12-addon-l10n-it-codici-carica
Requires-Dist: odoo12-addon-l10n-it-esigibilita-iva
Requires-Dist: odoo12-addon-l10n-it-fiscal-document-type
Requires-Dist: odoo12-addon-l10n-it-fiscalcode
Requires-Dist: odoo (<12.1dev,>=12.0a)
